{
  "station_code": "HB",
  "model_type": "RandomForestClassifier",
  "n_training_samples": 89,
  "n_test_samples": 23,
  "top1_accuracy": 0.21739130434782608,
  "top3_accuracy": 0.34782608695652173,
  "feature_importance": {
    "destination_encoded": 0.26531771453163583,
    "hour_of_day": 0.2516024773242155,
    "line_code_encoded": 0.22900692857297197,
    "minutes_since_track_used": 0.20732847072117455,
    "day_of_week": 0.046744408850002264,
    "is_amtrak": 0.0
  },
  "per_track_metrics": {
    "1": {
      "precision": 0.0,
      "recall": 0.0,
      "f1-score": 0.0,
      "support": 1.0
    },
    "2": {
      "precision": 0.5,
      "recall": 1.0,
      "f1-score": 0.6666666666666666,
      "support": 1.0
    },
    "3": {
      "precision": 0.0,
      "recall": 0.0,
      "f1-score": 0.0,
      "support": 2.0
    },
    "4": {
      "precision": 0.0,
      "recall": 0.0,
      "f1-score": 0.0,
      "support": 1.0
    },
    "5": {
      "precision": 0.0,
      "recall": 0.0,
      "f1-score": 0.0,
      "support": 1.0
    },
    "6": {
      "precision": 0.0,
      "recall": 0.0,
      "f1-score": 0.0,
      "support": 1.0
    },
    "7": {
      "precision": 0.0,
      "recall": 0.0,
      "f1-score": 0.0,
      "support": 2.0
    },
    "8": {
      "precision": 0.5,
      "recall": 1.0,
      "f1-score": 0.6666666666666666,
      "support": 2.0
    },
    "9": {
      "precision": 0.0,
      "recall": 0.0,
      "f1-score": 0.0,
      "support": 2.0
    },
    "10": {
      "precision": 0.0,
      "recall": 0.0,
      "f1-score": 0.0,
      "support": 1.0
    },
    "11": {
      "precision": 0.0,
      "recall": 0.0,
      "f1-score": 0.0,
      "support": 1.0
    },
    "12": {
      "precision": 0.0,
      "recall": 0.0,
      "f1-score": 0.0,
      "support": 2.0
    },
    "13": {
      "precision": 0.5,
      "recall": 0.5,
      "f1-score": 0.5,
      "support": 2.0
    },
    "14": {
      "precision": 0.0,
      "recall": 0.0,
      "f1-score": 0.0,
      "support": 1.0
    },
    "15": {
      "precision": 0.16666666666666666,
      "recall": 1.0,
      "f1-score": 0.2857142857142857,
      "support": 1.0
    },
    "16": {
      "precision": 0.0,
      "recall": 0.0,
      "f1-score": 0.0,
      "support": 1.0
    },
    "17": {
      "precision": 0.0,
      "recall": 0.0,
      "f1-score": 0.0,
      "support": 1.0
    },
    "accuracy": 0.21739130434782608,
    "macro avg": {
      "precision": 0.0980392156862745,
      "recall": 0.20588235294117646,
      "f1-score": 0.12464985994397759,
      "support": 23.0
    },
    "weighted avg": {
      "precision": 0.11594202898550726,
      "recall": 0.21739130434782608,
      "f1-score": 0.14285714285714285,
      "support": 23.0
    }
  }
}